{
  "id": "/fareNet",
  "$schema": "http://json-schema.org/draft-06/schema#",
  "title": "fareNet3.0",
  "description": "fareNet 3.0 includes journey only",
  "type": "object",
  "properties": {
    "journey": {
      "description": "Journey",
      "type": "object",
      "properties": {
        "airline": {
          "description": "airline",
          "type": "object",
          "properties": {
            "name": {
              "description": "name",
              "type": "string",
              "example": "EveryMundo"
            },
            "iataCode": {
              "description": "iataCode",
              "type": "string",
              "example": "EM"
            }
          }
        },
        "fullRoute": {
          "description": "fullRoute",
          "type": "string",
          "example": "SFO>MIA>JFK|JFK>SFO"
        },
        "priceSpecification": {
          "description": "priceSpecification",
          "type": "object",
          "properties": {
            "priceBeforeTaxesAndFees": {
              "description": "price",
              "type": "number",
              "example": 234.21
            },
            "totalPrice": {
              "description": "totalPrice",
              "type": "number",
              "example": 250.6
            },
            "taxAmount": {
              "description": "taxPrice",
              "type": "number",
              "example": 16.39
            },
            "additionalFeesAmount": {
              "description": "additionalFeesPrice",
              "type": "number",
              "example": 12
            },
            "currencyCode": {
              "description": "currency",
              "type": "string",
              "example": "USD"
            },
            "currencySymbol": {
              "description": "currencySymbol",
              "type": "string",
              "example": "$"
            },
            "pricingGroupId": {
              "description": "priceMarketId",
              "type": "string",
              "example": "USD-US"
            },
            "redemption": {
              "description": "redemption",
              "type": "object",
              "properties": {
                "unit": {
                  "description": "unit",
                  "type": "string",
                  "example": "MILES"
                },
                "amount": {
                  "description": "amount",
                  "type": "number",
                  "example": 1500
                }
              }
            }
          }
        },
        "passengerDetails": {
          "description": "passengerDetails",
          "type": "array",
          "items": {
            "type": "object",
            "properties": {
              "category": {
                "description": "Any passenger category following the format category[Age]To[Age]Count or category[Age]Plus",
                "type": "string",
                "example": "senior65Plus"
              },
              "mappedTo": {
                "description": "Field that passenger count is being mapped to under type Passenger",
                "type": "string",
                "example": "seniorCount"
              },
              "count": {
                "description": "Amount of passengers for a specific category",
                "type": "number",
                "example": 2
              }
            }
          }
        },
        "passenger": {
          "description": "passenger",
          "type": "object",
          "properties": {
            "count": {
              "description": "count",
              "type": "number",
              "example": 3
            },
            "seniorCount": {
              "description": "seniorCount",
              "type": "number",
              "example": 2
            },
            "adultCount": {
              "description": "adultCount",
              "type": "number",
              "example": 0
            },
            "youngAdultCount": {
              "description": "youngAdultCount",
              "type": "number",
              "example": 0
            },
            "childCount": {
              "description": "childCount",
              "type": "number",
              "example": 0
            },
            "infantInLapCount": {
              "description": "infantInLapCount",
              "type": "number",
              "example": 0
            },
            "infantInSeatCount": {
              "description": "infantInSeatCount",
              "type": "number",
              "example": 0
            }
          }
        },
        "fareTensor": {
          "description": "fareTensor",
          "type": "object",
          "properties": {
            "journeyType": {
              "description": "journeyType",
              "type": "string",
              "example": "ROUND_TRIP"
            },
            "cells": {
              "$ref": "./cells.schema.json"
              }
            }
        },
        "outboundFlight": {
          "description": "outboundFlight",
          "type": "object",
          "properties": {
            "boundType": {
              "description": "boundType",
              "type": "string",
              "example": "OUTBOUND"
            },
            "route": {
              "description": "route",
              "type": "string",
              "example": "SFO>JFK"
            },
            "priceSpecification": {
              "description": "priceSpecification",
              "type": "object",
              "properties": {
                "priceBeforeTaxesAndFees": {
                  "description": "price",
                  "type": "number",
                  "example": 750.12
                },
                "totalPrice": {
                  "description": "totalPrice",
                  "type": "number",
                  "example": 825.51
                },
                "taxAmount": {
                  "description": "taxPrice",
                  "type": "number",
                  "example": 75.39
                }
              }
            },
            "fareClassInput": {
              "description": "Name of the fare class given by airline in sentence case, e.g. Economy Basic",
              "type": "string",
              "example": "Economy Basic"
            },
            "fareClass": {
              "description": "fareClass",
              "type": "string",
              "example": "ECONOMY"
            },
            "departureAirportIataCode": {
              "description": "departureAirportIataCode",
              "type": "string",
              "example": "SFO"
            },
            "arrivalAirportIataCode": {
              "description": "arrivalAirportIataCode",
              "type": "string",
              "example": "JFK"
            },
            "departureDate": {
              "description": "Departure Date",
              "type": "string",
              "example": "2017-12-07"
            },
            "estimatedDuration": {
              "description": "estimatedDuration",
              "type": "string",
              "example": "PT9H45M"
            },
            "availableSeatsCount": {
              "description": "availableSeatsCount",
              "type": "string",
              "example": "9+"
            },
            "legs": {
              "description": "Leg is the operation of an aircraft from one scheduled departure station to its next scheduled arrival station", 
              "type": "array",
              "properties": {
                "flightNumber": {
                  "description": "flightNumber",
                  "type": "string",
                  "example": "EM110"
                },
                "route": {
                  "description": "route",
                  "type": "string",
                  "route": "SFO>MIA"
                },
                "departureAirport": {
                  "description": "departureAirport",
                  "type": "object",
                  "properties": {
                    "name": {
                      "description": "name",
                      "type": "string",
                      "example": "San Francisco Airport"
                    },
                    "iataCode": {
                      "description": "iataCode",
                      "type": "string",
                      "example": "SFO"
                    }
                  }
                },
                "departureTime": {
                  "description": "departureTime",
                  "type": "string",
                  "example": "06:35"
                },
                "arrivalAirport": {
                  "description": "arrivalAirport",
                  "type": "object",
                  "properties": {
                    "name": {
                      "description": "name",
                      "type": "string",
                      "example": "Miami International Airport"
                    },
                    "iataCode": {
                      "description": "iataCode",
                      "type": "string",
                      "example": "MIA"
                    }
                  }
                },
                "arrivalTime": {
                  "description": "arrivalTime",
                  "type": "string",
                  "example": "13:35"
                },
                "estimatedDuration": {
                  "description": "Total journey time including the combined air time and connection times.  In case of stopover, this may or may not include stopover durations. ISO 8601 format",
                  "type": "string",
                  "example": "PT6H30M"
                },
                "departureCity": {
                  "description": "departureCity",
                  "type": "object",
                  "properties": {
                    "name": {
                      "description": "name",
                      "type": "string",
                      "example": "San Francisco"
                    },
                    "cityCode": {
                      "description": "cityCode",
                      "type": "string",
                      "example": "SFO"
                    }
                  }
                },
                "departureCountry": {
                  "description": "departureCountry",
                  "type": "object",
                  "properties": {
                    "name": {
                      "description": "name",
                      "type": "string",
                      "example": "United States"
                    },
                    "isoCode": {
                      "description": "isoCode",
                      "type": "string",
                      "example": "US"
                    }
                  }
                },
                "arrivalCity": {
                  "description": "arrivalCity",
                  "type": "object",
                  "properties": {
                    "name": {
                      "description": "name",
                      "type": "string",
                      "example": "Miami"
                    },
                    "cityCode": {
                      "description": "cityCode",
                      "type": "string",
                      "example": "MIA"
                    }
                  }
                },
                "arrivalCountry": {
                  "description": "arrivalCountry",
                  "type": "object",
                  "properties": {
                    "name": {
                      "description": "name",
                      "type": "string",
                      "example": "United States"
                    },
                    "isoCode": {
                      "description": "isoCode",
                      "type": "string",
                      "example": "US"
                    }
                  }
                },
                "flightType": {
                  "description": "DOMESTIC, INTERNATIONAL",
                  "type": "string",
                  "example": "DOMESTIC"
                },
                "operatingAirline": {
                  "description": "operatingAirline",
                  "type": "object",
                  "properties": {
                    "name": {
                      "description": "name",
                      "type": "string",
                      "example": "EveryMundo"
                    },
                    "iataCode": {
                      "description": "iataCode",
                      "type": "string",
                      "example": "EM"
                    }
                  }
                },
                "aircraft": {
                  "description": "Aircraft brand",
                  "type": "string",
                  "example": "Boeing 747"
                },
                "additionalInfo": {
                  "description": "additionalInfo",
                  "type": "object",
                  "properties": {
                    "fields": {
                      "description": "fields",
                      "type": "array",
                      "items": {
                        "type": "object",
                        "properties": {
                          "name": {
                            "description": "",
                            "type": "string",
                            "example": "classOfService"
                          },
                          "value": {
                            "description": "",
                            "type": "string",
                            "example": "COACH_EC"
                          }
                        }
                      }
                    }
                  }
                }
              }
              }
            },
            "departureCity": {
              "description": "departureCity",
              "type": "object",
              "properties": {
                "name": {
                  "description": "name",
                  "type": "string",
                  "example": "San Francisco"
                },
                "cityCode": {
                  "description": "cityCode",
                  "type": "string",
                  "example": "SFO"
                }
              }
            },
            "departureCountry": {
              "description": "departureCountry",
              "type": "object",
              "properties": {
                "name": {
                  "description": "name",
                  "type": "string",
                  "example": "United States"
                },
                "isoCode": {
                  "description": "isoCode",
                  "type": "string",
                  "example": "US"
                }
              }
            },
            "arrivalCity": {
              "description": "arrivalCity",
              "type": "object",
              "properties": {
                "name": {
                  "description": "name",
                  "type": "string",
                  "example": "New York"
                },
                "cityCode": {
                  "description": "cityCode",
                  "type": "string",
                  "example": "NYC"
                }
              }
            },
            "arrivalCountry": {
              "description": "arrivalCountry",
              "type": "object",
              "properties": {
                "name": {
                  "description": "name",
                  "type": "string",
                  "example": "United States"
                },
                "isoCode": {
                  "description": "isoCode",
                  "type": "string",
                  "example": "US"
                }
              }
            },
            "flightType": {
              "description": "flightType",
              "type": "string",
              "example": "DOMESTIC"
            },
            "routeType": {
              "description": "routeType",
              "type": "string",
              "example": "CONNECTING"
            },
            "discount": {
              "$ref": "./discount.schema.json"
            },
            "additionalInfo": {
              "description": "additionalInfo",
              "type": "object",
              "properties": {
                "fields": {
                  "description": "fields",
                  "type": "array",
                  "items": {
                    "type": "object",
                    "properties": {
                      "name": {
                        "description": "",
                        "type": "string",
                        "example": "classOfService"
                      },
                      "value": {
                        "description": "",
                        "type": "string",
                        "example": "COACH_EC"
                      }
                    }
                  }
                }
              }
            }
        },
        "inboundFlight": {
          "description": "inboundFlight",
          "type": "object",
          "properties": {
            "boundType": {
              "description": "boundType",
              "type": "string",
              "example": "INBOUND"
            },
            "route": {
              "description": "route",
              "type": "string",
              "example": "JFK>SFO"
            },
            "priceSpecification": {
              "description": "priceSpecification",
              "type": "object",
              "properties": {
                "priceBeforeTaxesAndFees": {
                  "description": "price",
                  "type": "number",
                  "example": 750.12
                },
                "totalPrice": {
                  "description": "totalPrice",
                  "type": "number",
                  "example": 825.51
                },
                "taxAmount": {
                  "description": "taxPrice",
                  "type": "number",
                  "example": 75.39
                }
              }
            },
            "fareClassInput": {
              "description": "fareClassInput",
              "type": "string",
              "example": "Economy"
            },
            "fareClass": {
              "description": "fareClass",
              "type": "string",
              "example": "ECONOMY"
            },
            "departureAirportIataCode": {
              "description": "departureAirportIataCode",
              "type": "string",
              "example": "JFK"
            },
            "arrivalAirportIataCode": {
              "description": "arrivalAirportIataCode",
              "type": "string",
              "example": "SFO"
            },
            "departureDate": {
              "description": "Departure Date",
              "type": "string",
              "example": "2017-12-10"
            },
            "estimatedDuration": {
              "description": "estimatedDuration",
              "type": "string",
              "example": "PT9H45M"
            },
            "availableSeatsCount": {
              "description": "availableSeatsCount",
              "type": "string",
              "example": "9+"
            },
            "legs": {
              "description": "legs",
              "type": "array",
              "items": {
                "type": "object"
              }
            },
            "departureCity": {
              "description": "departureCity",
              "type": "object",
              "properties": {
                "name": {
                  "description": "name",
                  "type": "string",
                  "example": "New York"
                },
                "cityCode": {
                  "description": "cityCode",
                  "type": "string",
                  "example": "NYC"
                }
              }
            },
            "departureCountry": {
              "description": "departureCountry",
              "type": "object",
              "properties": {
                "name": {
                  "description": "name",
                  "type": "string",
                  "example": "United States"
                },
                "isoCode": {
                  "description": "isoCode",
                  "type": "string",
                  "example": "US"
                }
              }
            },
            "arrivalCity": {
              "description": "arrivalCity",
              "type": "object",
              "properties": {
                "name": {
                  "description": "name",
                  "type": "string",
                  "example": "San Francisco"
                },
                "cityCode": {
                  "description": "cityCode",
                  "type": "string",
                  "example": "SFO"
                }
              }
            },
            "arrivalCountry": {
              "description": "arrivalCountry",
              "type": "object",
              "properties": {
                "name": {
                  "description": "name",
                  "type": "string",
                  "example": "United States"
                },
                "isoCode": {
                  "description": "isoCode",
                  "type": "string",
                  "example": "US"
                }
              }
            },
            "flightType": {
              "description": "flightType",
              "type": "string",
              "example": "DOMESTIC"
            },
            "routeType": {
              "description": "routeType",
              "type": "string",
              "example": "NONSTOP"
            },
            "discount": {
              "$ref": "./discount.schema.json"
            },
            "additionalInfo": {
                  "description": "additionalInfo",
                  "type": "object",
                  "properties": {
                    "fields": {
                      "description": "fields",
                      "type": "array",
                      "items": {
                        "type": "object",
                        "properties": {
                          "name": {
                            "description": "",
                            "type": "string",
                            "example": "classOfService"
                          },
                          "value": {
                            "description": "",
                            "type": "string",
                            "example": "COACH_EC"
                          }
                        }
                      }
                    }
                  }
            }
          }
        },
        "departureDate": {
          "description": "departureDate",
          "type": "string",
          "example": "2017-12-07"
        },
        "returnDate": {
          "description": "returnDate",
          "type": "string",
          "example": "2017-12-10"
        },
        "journeyType": {
          "description": "journeyType",
          "type": "string",
          "example": "ROUND_TRIP"
        },
        "isCodeShare": {
          "description": "isCodeShare",
          "type": "boolean",
          "example": true
        },
        "flightType": {
          "description": "flightType",
          "type": "string",
          "example": "DOMESTIC"
        },
        "segmentCount": {
          "description": "segmentCount",
          "type": "number",
          "example": 2
        },
        "flightCount": {
          "description": "flightCount",
          "type": "number",
          "example": 3
        },
        "discount": {
          "$ref": "./discount.schema.json"
        }
      }
    },
    "page": {
      "description": "WebPage",
      "type": "object",
      "properties": {
        "name": {
          "description": "The name of the page",
          "type": "string",
          "example": "flights from miami to berlin"
        },
        "url": {
          "description": "The page url",
          "type": "string",
          "example": "flights.everymundo.com/en/flights-from-miami-to-berlin"
        },
        "hostName": {
          "description": "Host name",
          "type": "string",
          "example": "flights.everymundo.com"
        },
        "languageIsoCode": {
          "description": "Language ISO 639-1 code",
          "type": "string",
          "example": "en"
        },
        "siteEdition": {
          "description": "Site edition combination of ISO codes for language and country",
          "type": "string",
          "example": "en-US"
        }
      }
    },
    "device": {
      "allOf": [
        {"$ref": "./device.schema.json"},
        {"required": ["category", "screenResolution", "operatingSystem"]}
      ],
      "additionalProperties": false
    },
    "metadata": {
      "description": "Metadata",
      "type": "object",
      "properties": {
        "app": {
          "description": "App",
          "type": "object",
          "properties": {
              "name": {
                  "description": "Farenet | GoogleITA UA Client",
                  "type":"string",
                  "example": "Farenet | GoogleITA UA Client"
              },
              "version": {
                  "description": "Version of the program that generated the record",
                  "type":"string",
                  "example": "2.1.0"
              },
              "datasource": {
                  "description": "IBE_FLIGHT_SELECTION, IBE_CONFIRMATION, IBE_PASSENGER_INFO, IBE_CHECK, IBE_EXTRAS, IBE_SEATS_SELECTION, IBE_PAYMENT",
                  "type":"string",
                  "example": "IBE_FLIGHT_SELECTION"   
              }
          }
        },
        "trackingId": {
          "description": "Unique identifier created through module interactions for event tracking",
          "type": "string",
          "example": "RTJFKFRA2017073120170824$0_123456KARIN"
        },
        "schemaVersion": {
          "description": "Schema version of Data Standards",
          "type": "number",
          "example": "0.0.1"
        }
    }
    }
  },
  "required": ["journey", "page", "device", "metadata"],
  "links": [
    {
      "title": "Kat",
      "description": "Kattest",
      "rel": "self",
      "href": "/fareNet",
      "method": "GET",
      "targetSchema": {
        "rel": "self"
      }
    }
  ]
}