{
  "_id": "16245813386333721.7355aagg-00275",
  "geotarget": "CJB",
  "routelocale": "Domestic",
  "accountid": "9362032036",
  "campaignname": "GS:en-IN_NB\\CC-Dest={CJB}>XX>TRV/Geo@CJB",
  "campaignid": "397909737",
  "adgroupname": "GS:en-IN_NB\\DD={CJB}>XX>TRV/PH@Trivandrum",
  "adgroupid": "21219792897",
  "airlinename": "EM Airlines",
  "airlinecode": "EM",
  "accountname": "EM_IN (en)",
  "origin": "CJB",
  "destination": "TRV",
  "routetype": "Connecting",
  "searchengine": "Google",
  "campaigntype": "Non-Brand",
  "market": "IN",
  "language": "en",
  "keywordtype": "Destination",
  "keywordgroup": "Trivandrum",
  "audience": "PS-PY(+30d)",
  "specialcampaign": "CPA",
  "marketingnetwork": "Search",
  "locationtype": "City>City",
  "matchtype": "PH",
  "input_key": "Google&&EM_IN (Dom)&&GS:en-IN_NB\\CC-Dest={CJB}>XX>TRV/Geo@CJB&&GS:en-IN_NB\\DD={CJB}>XX>TRV/PH@Trivandrum",
  "parserversion": "4.5.6",
  "parseregexid": "EveryMundoNonBrand1",
  "parsebatchid": "202106250030",
  "__v": 1,
  "__createdat": "2021-06-25 00:35:38"
}
