{
  "locationcode": "AAD",
  "locationcodetype": "AIRPORT",
  "airportgeoid": "123456",
  "airportnames": [{
    "en": "Adado Airport",
    "es": "Aeroporto de Adado",
    "fr": "Aéroport Adado",
    "pt": "Aeroporto de Adado"
  }],
  "citygeoid": "1234567",
  "citynames": [{
    "en": "Adado",
    "es": "Adado",
    "fr": "Adado",
    "pt": "Adão"
  }],
  "stateisocode": null,
  "stategeoid": "90735920",
  "countryisocode": "SO",
  "countryatpcocode": "SO",
  "countrygeoid": "9752839",
  "countrynames": [{
    "en": "Somalia",
    "es": "Somalia",
    "fr": "Somalie",
    "pt": "Somália"
  }],
  "areaiatacode": "2",
  "continentcode": "AF",
  "subregioniatacode": "",
  "regioniatacode": "AFR",
  "zoneatpcocode": "233",
  "latitude": "6.09682",
  "longitude": "46.63825",
  "timezoneid": "Africa/Mogadishu",
  "timezoneoffset": "UTC/GMT+3",
  "discontinueddate": "2003-01-12",
  "effectivedate": "",
  "isactive": false
}
